{
    "total":26,
    "1":{
        "ar":"بِسْمِ اللهِ الرَّحْمَنِ الرَّحِيْمِ",
        "eng":"In the name of Allah Most Gracious and Merciful"
    },
    "2":{
        "ar":"الْحَمْدُ للهِ رَبِّ الْعَالَمِيْنَ، حَمْدَاً يُوَافِيْ نِعَمَهُ وَيُكَافِئُ مَزِيْدَهُ.",
        "eng":"Praise be to Allah, Lord of the Worlds, equivalent to His grace and comparable to His Extras."
    },
    "3":{
        "ar":"يَا رَبَّنَا لَكَ الْحَمْدُ كَمَا يَنْبَغِيْ لِجَلَاْلِ وَجْهِكَ وَلِعَظِيْمِ سُلْطَانِكْ.",
        "eng":"O Lord, Praise belongs to You that befits the Awe of Your Face and the Grandeur of Your Power."
    },
    "4":{
        "ar":"الَّلهُمَّ صَلِّ عَلَى سَيِّدِنَا مُحَمَّدٍ وَعَلَى آلِهِ وَصَحْبِهِ وَمَنْ تَبِعَهُمْ بِإِحْسَانٍ إِلَى يَوْمِ الدِّيْنِ.",
        "eng":"O Allah shower Your Salaat on our Most Honorable Muhammad, his family and his Companions, and those who follow them in excellence to the Day of Payback."
    },
    "5":{
        "ar":"اللَّهُمَّ ارْحَمْنَا بالقُرْآنِ الْعَظِيمْ، وَاجْعَلهُ لَنَا إِمَاماً وَنُوراً وَهُدًى وَرَحْمَةً.",
        "eng":"O Allah shower Your Mercy on us by the Great Quran and make the Quran our leader, enlightenment, guidance and grace."
    },
    "6":{
        "ar": "اللَّهُمَّ ذَكِّرْنَا مِنْهُ مَا نُسِّيْنَا، وَعَلِّمْنَا مِنْهُ مَا جُهِّلْنَا، وَارْزُقْنَا تِلاَوَتَهُ آنَاءَ اللَّيْلِ وَأَطْرَافَ النَّهَارِ، وَاجْعَلْهُ لَنَا حُجَّةً يَوْمَ لِقَاْئِكَ يَا رَبَّ العَالَمِينْ.",
        "eng":"O Allah bring back to mind what we have been made to forget, teach us what we have been made to ignore, provide us with its recitation day and night, and make the Quran our supporter when we meet You, Lord of beings!"
    }, 
    "7":{
        "ar":"اللَّهُمَّ اجْعَلْنَا مِمَّنْ يُحِلُّ حَلَاْلَهُ وَيُحَرِّمُ حَرَاْمَهُ، وَيَعْمَلُ بِمُحْكَمِهِ، وَيُؤْمِنُ بِمُتَشَابِهِهْ، وَيَتْلُوْهُ حَقَّ تِلَاْوَتِهْ.",
        "eng":"O Allah make us among those who observe the Halal in the Quran, abstain from the Haram therein, work on its clear verses, believe in its ambiguous verses and recite it the way it should be recited."
    },
     "8":{
        "ar":"اللَّهُمَّ اجْعَلْنَا مِمَّنْ يُقِيْمُ حُرُوْفَهُ وَحُدُوْدَهُ، وَاجْعَلْنَا مِنْ أَهْلِ الْقُرْآنْ الَّذِيْنَ هُمْ أَهْلُكَ وَخَاصَّتُكَ يَا أَرْحَمَ الرَّاْحِمِيْن.",
        "eng":"O Allah let us stand by its letters and limits, and make us among the people of the Quran, who are Your people and Special Circle; You are the Most Merciful."
    },
    
    
    "9":{
        "ar":"اللَّهُمَّ اجْعَلِ الْقُرْآنَ لِقُلُوْبِنَا ضِيَاءً، وَلِأَبْصَاْرِنَا جَلَاءً، وَلِأَسْقَامِنَا دَوَاءً، وَلِذُنُوْبِنَا مُمَحِّصَاً، وَمِنَ النَّارِ مُخَلِّصَاً.",
        "eng":"O Allah Make the Quran an enlightenment for our hears, clarity for our insight, healing for our sickness, redeemer for our sins, and a salvation from the Hell Fire."
    }, 
    
    "10":{
        "ar":"اللَّهُمَّ أَلْبِسْنَا بِهِ الْحُلَلْ، وَأَسْكِنَّا بِهِ الظَّلَلْ، وَأَسْبِغْ عَلَيْنَا بِهِ النِّعَمْ، وَادْفَعْ عَنَّا بِهِ النِّقَمْ، وَاجْعَلْنَا بِهِ عِنْدَ الْجَزَاءِ مِنَ الْفَائِزِينْ، وَعِنْدَ النَّعْمَاءِ مِنَ الشَّاكِرِيْنَ، وَعِنْدَ الْبَلَاْءِ مِنَ الصَّابِرِيْنَ، وَلَاْ تَجْعَلْنَا مِمَّنْ اسْتَهْوَتْهُ الشَّيَاْطِيْن، فَشَغَلَتْهُ بِالدُّنْيَا عَنِ الدِّينْ.",
        "eng":"O Allah through the Quran, clothe us suits, house us in gardens, extend Your shadow on us, protect us from vengeance, make us winners on the Reward Day, grateful on blessing, and patient on inflictions. Do not make us among those who are attracted by the Devil and distracted by worldly matters from the faith."
    },
    "11":{
        "ar":"اللَّهُمَّ إِنَّا عَبِيْدُكْ، أَبْنَاءُ عَبِيْدِكْ، أَبْنَاءُ إِمَائِكْ، نَوَاصِيْنَا بِيَدِكْ، مَاضٍ فِيْنَا حُكْمُكْ، عَدْلٌ فِيْنَا قَضَاؤُكْ، نَسْأَلُكَ بِكُلِّ اسْمٍ هُوَ لَكَ، سَمَّيْتَ بِهِ نَفْسَكَ أَوْ أَنْزَلْتَهُ فِيْ كِتَابِكْ، أَوْ عَلَّمْتَهُ أَحَداً مِنْ خَلْقِكْ، أَوِ اسْتَأْثَرْتَ بِهِ فِيْ عِلْمِ الْغَيْبِ عِنْدَكْ، أَنْ تَجْعَلَ الَّلهُمَّ الْقُرْآنَ الْعَظِيْمَ رَبِيْعَ قُلُوْبِنَا، وَنُوْرَ أَبْصَاْرِنَا، وَجَلَاْءَ أَحْزَاْنِنَا، وَذَهَاْبَ هُمُوْمِنَا وَغُمُومِنَا.",
        "eng":"O Allah  we are Your servants, children of Your servants; our forelocks are in Your Hand; Your rule governs us; just is Your judgement. We ask you by every name of Yours by which You called Yourself, descended in Your Book, taught to anyone of your creation, or kept in the knowledge of the unseen with You, to make the Great Quran the Spring of our hearts, the light of our sight, the clearance of our sorrows and the disappearance of our worries and concerns."
    },
    "12":{
        "ar":"وَاجْعَلْهُ قَائِدَاً لَنَا إِلَى رِضْوَانِكَ وَجَنَّتِكَ يَا رَبَّ الْعَالَمِيْنْ،",
        "eng":"And make him our leader to your satisfaction and paradise, O Lord of the worlds,"
    },
    "13":{
        "ar":"اللَّهُمَّ اشْدُدْ بِهِ أَمْرَنَا وَارْفَعْ بِهِ ذِكْرَنَا، وَضَعْ بِهِ عَنَّا وِزْرَنَا، وَضَعْ بِهِ عَنَّا وِزْرَنَا وَإصْرَنَا، وَاجْعَلْهُ فِيْ الْآخِرَةِ ذُخْرَنَا.",
        "eng":"O Allah  by the Quran fix our issues, speak highly of us, redeem our load of sins, and make it in the hereafter our treasure. "
    },
    "14":{
        "ar":"اللَّهُمَّ أَصْلِحْ لَنَا دِينَنَا الَّذِي هُوَ عِصْمَةُ أَمْرِنَا، وَأَصْلِحْ لَنَا دُنْيَانَا الَّتِي فِيهَا مَعَاشُنَا، وَأَصْلِحْ لَنَا آخِرَتَنَا الَّتِي إِلَيْهَا مَعَادُنَا، وَاجْعَلِ الحَيَاةَ زِيَادَةً لَنَا فِي كُلِّ خَيْرٍ وَاجْعَلِ المَوْتَ رَاحَةً لَنَا مِنْ كُلِّ شَرٍّ.",
        "eng":"O Allah fix for us our religion, which is our protection; fix for us this world where we earn our livelihood; and fix for us our hereafter, to which we are returning. Make life an increase for us in all good and make death a rest for us from all evil."
    },
    "15":{
        "ar":"اللَّهُمَّ اجْعَلْنَا لِلْقُرآنِ الْعَظِيْمِ ذَاكِرِيْنْ، وَبِهِ عَامِلِينْ، ولِلنَّعْمَاءِ شَاكِرِينْ، وَفِيْ الضَّرَّاءِ صَابِرِينْ، وَلِلْفَرَائِضِ مُؤَدِّينْ، وَبِرَسُوْلِكَ صَلَّى اللهُ عَلَيْهِ وَسَلَّم مُقْتَدِينْ، وَلِسُنَّتِهِ مُتَّبِعِيْنْ، وَبِالْأعْمَالِ مُخْلِصِينْ، وَبِالْآيَاتِ مُوقِنِينْ، وَلِلْإِخْوَانِ مُحْسِنِينْ، وَبِالطَّاعَاتِ آمِرِينْ، وَعَنِ الْـمَعَاصِي زَاجِرِينْ، وَبِالْقِسْطِ قَائِمِينْ، وَبِالنَّهَارِ صَائِمِينْ، وَبِالَّليْلِ قَائِمِينْ، وَبِالْجِنَانِ فَائِزينْ، وَإِلَى وَجْهِكَ الْكَرِيمِ نَاظِرِينْ.",
        "eng":"O Allah make us reciters of the Great Quran and committed to its guidance. Make us grateful for the blessing, tolerant of the hardship, committed to Your commandments, emulators of Your Messenger (peace and blessings of Allah be upon him), and followers of his Sunnah. Make us faithful in our deeds, believers in the Signs, and kind to brothers. Make us bid for obedience, forbid disobedience, and observant of justice. Make us fast the day and stay up at night in devotion. Make us ultimate winners of Paradise, and onlookers to Your Honorable Countenance. "
    },
    "16":{
        "ar":"اللَّهُمَّ حَسِّنْ بِالْقُرْآنِ أَخْلَاقَنَا، وَنَوِّرْ بِهِ قُلُوبَنَا، وَاسْتُرْ بِهِ عُيُوبَنَا، وَفَرِّجْ بِهِ كُرُوبَنَا، وَأَصْلِحْ بِهِ ذَاتَ بَيْنِنَا، وَانْصُرْنَا بِهِ عَلَى مَنْ ظَلَمَنَا، وَاجْعَلْهُ لَنَا شَافِعَاً وَمُعِيْناً.",
        "eng":"O Allah improve by the Quran our morals, enlighten our hearts, cover our shortcomings, relieve our anguish, reconcile our disputes, give us victory over those who wronged us, and make it our intercessor and helper."
    },
    "17":{
        "ar":"اللَّهُمَّ  لَاْ تَدَعْ لَنَا ذَنْبَاً إِلَّا غَفَرْتَهْ، وَلَاْ هَمَّاً إِلَّا فَرَّجْتَهْ، وَلَا كَرْبَاً إِلَّا نَفَّسْتَهْ، وَلَا ضُرّاً إِلَّا كَشَفْتَهْ، وَلَاْ عَيْبَا إِلَّا سَتَرْتَهْ، وَلَاْ عَسِيْرَاً إِلَّاْ يَسَّرْتَهْ، وَلَاْ مَرِيْضَاً إِلَّا شَافَيْتَهْ، وَلَاْ ضَالَّاً إِلَّا هَدَيْتَهْ، وَلَاْ دَيْنَاً إِلَّاْ قَضَيْتَهْ، وَلَاْ عَدُوَّاً إِلَّاْ خَذَلْتَهْ، وَلَاْ حَاجَةً مِنْ حَوَائِجِ الدُّنْيَا وَالْآخِرَةِ لَنَا فَيْهَا صَلَاْحٌ وَلَكَ فِيْهَا رِضَاً إِلَّا قَضَيْتَهَا يَا أَرْحَمَ الرَّاحِمِيْنْ. ",
        "eng":"O Allah  do not leave us any sin except You forgive, any concern except You relieve, any anguish except You remove, any harm except You clear, any shortcoming except You cover, any difficulty except You ease, any sick except You heal, any misled except You guide, any debt except You settle, any enemy except You defeat, and any need of the needs of this world or the hereafter, wherein resides goodness for us and pleasure for You, except You fulfill, O Most Merciful of all."
    },
    "18":{
        "ar":"اللَّهُمَّ  أَعْطِنَا وَلَاْ تَحْرِمْنَا، وَأَكْرِمْنَا وَلَا تُهِنَّا، وَزِدْنَا وَلَا تَنْقُصْنَا، وَآثِرْنَا وَلَا تُؤْثِرْ عَلَيْنَا، وَارْفَعْنَا وَلَا تَضَعْنَا، وَاجْعَلْنَا مِنْ عِبَادِكَ الصَّالِحِينْ.",
        "eng":"O Allah give us and do not deprive us; honor us and do not humiliate us; increase us and do not decrease us; prefer us and do not prefer others over us; honor us up and do not humiliate us; and make us among Your righteous servants."
    },

    "19":{
        "ar":"اللَّهُمَّ  اقْسِمْ لَنَا مِنْ خَشْيَتِكَ مَا تَحُولُ بِهِ بَيْنَنَا وَبَيْنَ مَعْصِيَتِكَ، وَمِنْ طَاعَتِكَ مَا تُبَلِّغُنَا بِهَا جَنَّتَكَ، وَمِنَ اليَقِينِ مَا تُهَوِّنُ بِهِ عَلَيْنَا مَصَائِبَ الدُّنْيَا، وَمَتِّعْنَا الَّلهُمَّ بِأَسْمَاعِنَا وَأَبْصَارِنَا وَقُوَّتِنَا أَبَدَاً مَا أَبْقَيْتَنَا، وَاجْعَلْهُ الوَارِثَ مِنَّا، وَاجْعَلْ ثَأْرَنَا عَلَى مَنْ ظَلَمَنَا، وَانْصُرْنَا عَلَى مَنْ عَادَانَا، وَلاَ تجْعَلْ مُصِيبَتَنَا فِي دِينِنَا، وَلاَ تَجْعَلِ الدُّنْيَا أَكْبَرَ هَمِّنَا وَلَا مَبْلَغَ عِلْمِنَا، وَاجْعَلِ الْجَنَّةَ مَأْوَانَا، فِيْ صُحْبَةِ النَّبِيِّينَ والصِّدِّيْقِيْنَ والشُّهَدَاءِ والصَّالِحِينْ، وَحَسُنَ أُولَئِكَ رَفِيْقاً. ",
        "eng":"O Allah provide us with fear of You that would prevent us from Your disobedience; provide us with obedience to You that gets us to Your Paradise; provide us with certainty by which You trivialize the calamities of this world. O Allah let us enjoy our hearing, sight, and faculties for lifetime. Direct our revenge on those who wronged us and let us win over those who opposed us. Do not make misfortune in our religion. Do not make this world our greatest concern, nor our ultimate level of knowledge. Make Paradise our home, in the company of Prophets, Firm Believers, Martyrs and Righteous; these are the best companions. "
    },
    "20":{
        "ar":"رَبَّنَا لَا تُؤَاخِذْنَا إِنْ نَسِيْنَا أَوْ أَخْطَأْنَا، رَبَّنَا وَلَا تَحْمِلْ عَلَيْنَا إِصْرَاً كَمَا حَمَلْتَهُ عَلَى الَّذِيْنَ مِنْ قَبْلِنَا، رَبَّنَا وَلَا تُحَمِّلْنَا مَا لَا طَاقَةَ لَنَا بِهِ، وَاعْفُ عَنَّا وَاغْفِرْ لَنَا وَارْحَمْنَا، وَاعْفُ عَنَّا وَاغْفِرْ لَنَا وَارْحَمْنَا، وَاعْفُ عَنَّا وَاغْفِرْ لَنَا وَارْحَمْنَا، أَنْتَ مَوْلَانَا فَانْصُرْنَا عَلَى الْقَوْمِ الْكَافِرِينْ.",
        "eng":"Our Lord, do not blame us if we forget or make a mistake; our Lord, and do not bear on us a burden like that You burdened those before us; our Lord, and do not bear us what we cannot afford. Pardon us, forgive us and have mercy on us; pardon us, forgive us, have mercy on us; pardon us, forgive us and have mercy on us. You are our Guardian, so let us win over the disbelieving people."
    },
    "21":{
        "ar":"رَبَّنَا هَبْ لَنَا مِنْ أَزْوَاجِنَا وَذُرِّيَّاتِنَا قُرَّةَ أَعْيُنٍ وَاجْعَلْنَا لِلْمُتَّقِيْنَ إِمَامَا،",
        "eng":"May God grant us from our husbands and offspring apple of our eyes and make us leaders of the Godfearing."
    },

    "22":{
        "ar":"اللَّهُمَّ  حَبِّبْ إِلَيْنَا الْإِيْمَانَ وَزَيِّنْهُ فِيْ قُلُوْبِنَا،  اللَّهُمَّ حَبِّبْ إِلَيْنَا الْإِيْمَانَ وَزَيِّنْهُ فِيْ قُلُوْبِنَا، اللَّهُمَّ حَبِّبْ إِلَيْنَا الْإِيْمَانَ وَزَيِّنْهُ فِيْ قُلُوْبِنَا، وَكَرِّهْ إِلَيْنَا الْكُفْرَ والْفُسُوقَ وَالْعِصْيَانْ، وَاجْعَلْنَا مِنَ الرَّاشِدِينْ.",
        "eng":"Oh Allah let us love faith and adorn it in our hearts,  Oh Allah let us love faith us and adorn it in our hearts, Oh Allah let us love faith and adorn it in our hearts; and let us hate us infidelity, immorality and disobedience, and make us of the wise."
    },
    "23":{
        "ar":"رَبَّنَا اغْفِرْ لَنَا وَلِإِخْوَانِنَا الَّذِيْنَ سَبَقُوْنَا بِالْإِيْمَانِ، وَلَاْ تَجْعَلْ فِيْ قُلُوْبِنَا غِلَّاً لِلَّذِيْنَ آمَنُوْارَبَّنَا إِنَّكَ رَؤُوْفٌ رَحِيْمْ.",
        "eng":"Our Lord, forgive us and our brothers who preceded us by faith, and do not put in our hearts hatred for those who believed.Lord, you are Gracious and Merciful."
    },
    
    "24":{
        "ar":"رَبَّنَا آتِنَا فِيْ الدُّنْيَا حَسَنَةً وَفِيْ الْآخِرَةِ حَسَنَةً وَقِنَا عَذَابَ النَّارِ.",
        "eng":"Our Lord bring us goodness in this world and goodness in the hereafter and save us from the torment of fire."
    },
    "25":{
        "ar":"وَصَلَّى اللهُ عَلَى سَيِّدِنَا مُحَمَّدٍ النَّبِيِّ الْأُمِّيِّ الطَّاهِرِ الزَّكِيِّ وَعَلَى آلِهِ وَصَحْبِهِ وَسَلَّمْ.",
        "eng":"May Allah bless our master Muhammad, the unlettered and pure and refined Prophet, and his family and companions."
    },
    "26":{
        "ar":"سُبْحَانَ رَبِّكَ رَبِّ الْعِزَّةِ عَمَّا يَصِفُونَ * وَسَلَامٌ عَلَى الْمُرْسَلِينَ * وَالْحَمْدُ لِلَّهِ رَبِّ الْعَالَمِينَ *",
        "eng":"Glory be to your Lord, Lord of Might, from what they ascribe; peace be upon the messengers; and Praise be to Allah, Lord of the Worlds."
    }

    
}